{"_type":"export","__export_format":4,"__export_date":"2022-01-05T15:39:33.511Z","__export_source":"insomnia.desktop.app:v2021.7.2","resources":[{"_id":"req_ab31131b5baf49d7a8e8947a34b58351","parentId":"wrk_e521a4a9150542dba55e917aca255462","modified":1641250011912,"created":1641245656135,"url":"https://api.synthesia.io/v2/videos","name":"synthesia Create","description":"","method":"POST","body":{"mimeType":"application/json","text":"{\n        \"test\": \"true\",\n        \"input\": [\n            {\n                \"scriptText\": \"Teenage Mutant Ninja Turtles\",\n                \"avatar\": \"anna_costume1_cameraA\", \n                \"background\": \"green_screen\"\n            }\n        ]\n    }"},"parameters":[],"headers":[{"id":"pair_1bd84ae610604909b2234feca7ae3497","name":"Authorization","value":"f01ff778bf8841cbc85d0d3cfd4ad3c9","description":""},{"id":"pair_2abd94e12f35444c901a502fe2d12b14","name":"Content-Type","value":"application/json","description":""}],"authentication":{},"metaSortKey":-1641245656135,"isPrivate":false,"settingStoreCookies":true,"settingSendCookies":true,"settingDisableRenderRequestBody":false,"settingEncodeUrl":true,"settingRebuildPath":true,"settingFollowRedirects":"global","_type":"request"},{"_id":"wrk_e521a4a9150542dba55e917aca255462","parentId":null,"modified":1640930393779,"created":1640930393779,"name":"avatar","description":"","scope":"collection","_type":"workspace"},{"_id":"req_22dc0aa385a64c698b79b0cae3ebd90a","parentId":"wrk_e521a4a9150542dba55e917aca255462","modified":1641261913886,"created":1641250024225,"url":"https://api.synthesia.io/v2/videos/f1ba64ad-b398-46cc-9007-0ce8ad58ecb9","name":"synthesia Get Status","description":"","method":"GET","body":{"mimeType":"text/plain","text":""},"parameters":[],"headers":[{"id":"pair_1bd84ae610604909b2234feca7ae3497","name":"Authorization","value":"f01ff778bf8841cbc85d0d3cfd4ad3c9","description":""},{"id":"pair_2abd94e12f35444c901a502fe2d12b14","name":"Content-Type","value":"text/plain","description":""}],"authentication":{},"metaSortKey":-1641088034123.5,"isPrivate":false,"settingStoreCookies":true,"settingSendCookies":true,"settingDisableRenderRequestBody":false,"settingEncodeUrl":true,"settingRebuildPath":true,"settingFollowRedirects":"global","_type":"request"},{"_id":"req_d29ad4bf78de4f098e3666f3ad852f16","parentId":"wrk_e521a4a9150542dba55e917aca255462","modified":1640930424942,"created":1640930412112,"url":"http://127.0.0.1:8080/ping","name":"ping","description":"","method":"GET","body":{},"parameters":[],"headers":[],"authentication":{},"metaSortKey":-1640930412112,"isPrivate":false,"settingStoreCookies":true,"settingSendCookies":true,"settingDisableRenderRequestBody":false,"settingEncodeUrl":true,"settingRebuildPath":true,"settingFollowRedirects":"global","_type":"request"},{"_id":"req_18c8ef30272e4de2bce763617fbe2809","parentId":"wrk_e521a4a9150542dba55e917aca255462","modified":1640932329562,"created":1640931850831,"url":"http://127.0.0.1:8080/tokenisvalid","name":"token","description":"","method":"GET","body":{},"parameters":[],"headers":[{"id":"pair_12e4f342d28e457ca368aaefc4c9626f","name":"X-Vocinity-Token","value":"secure_token","description":"","disabled":false}],"authentication":{},"metaSortKey":-1640930412087,"isPrivate":false,"settingStoreCookies":true,"settingSendCookies":true,"settingDisableRenderRequestBody":false,"settingEncodeUrl":true,"settingRebuildPath":true,"settingFollowRedirects":"global","_type":"request"},{"_id":"req_797a29aa73aa4b8493400fa113753fcd","parentId":"wrk_e521a4a9150542dba55e917aca255462","modified":1641262162612,"created":1641235283965,"url":"http://127.0.0.1:8080/avatar","name":"create Avatar","description":"","method":"POST","body":{"mimeType":"application/json","text":"{\n  \"avatar\": \"anna_costume1_cameraA\", \n  \"background\": \"green_screen\", \n  \"overlayImage\": \"vocinity.png\", \n  \"scriptText\": \"You have a friend on me\"\n}"},"parameters":[],"headers":[{"id":"pair_12e4f342d28e457ca368aaefc4c9626f","name":"X-Vocinity-Token","value":"secure_token","description":"","disabled":false},{"name":"Content-Type","value":"application/json","id":"pair_07a6893e54724aff941f7729efc293d5"}],"authentication":{},"metaSortKey":-1640930412037,"isPrivate":false,"settingStoreCookies":true,"settingSendCookies":true,"settingDisableRenderRequestBody":false,"settingEncodeUrl":true,"settingRebuildPath":true,"settingFollowRedirects":"global","_type":"request"},{"_id":"req_b3817af22d904cbdb4fb2286635681ea","parentId":"wrk_e521a4a9150542dba55e917aca255462","modified":1641252271260,"created":1641249981600,"url":"http://127.0.0.1:8080/avatar/f704c1ca-dc07-4d78-acc1-01988efcfe5e","name":"get Avatar Status","description":"","method":"GET","body":{"mimeType":"application/json","text":""},"parameters":[],"headers":[{"id":"pair_12e4f342d28e457ca368aaefc4c9626f","name":"X-Vocinity-Token","value":"secure_token","description":"","disabled":false},{"name":"Content-Type","value":"application/json","id":"pair_07a6893e54724aff941f7729efc293d5"}],"authentication":{},"metaSortKey":-1640930411987,"isPrivate":false,"settingStoreCookies":true,"settingSendCookies":true,"settingDisableRenderRequestBody":false,"settingEncodeUrl":true,"settingRebuildPath":true,"settingFollowRedirects":"global","_type":"request"},{"_id":"req_0fdcd1d4a09f48928a7db146b78733cb","parentId":"wrk_e521a4a9150542dba55e917aca255462","modified":1641252260827,"created":1641252251148,"url":"http://127.0.0.1:8080/avatar/download/f704c1ca-dc07-4d78-acc1-01988efcfe5e', ","name":"download Avatar Status","description":"","method":"GET","body":{"mimeType":"application/json","text":""},"parameters":[],"headers":[{"id":"pair_12e4f342d28e457ca368aaefc4c9626f","name":"X-Vocinity-Token","value":"secure_token","description":"","disabled":false},{"name":"Content-Type","value":"application/json","id":"pair_07a6893e54724aff941f7729efc293d5"}],"authentication":{},"metaSortKey":-1640930411937,"isPrivate":false,"settingStoreCookies":true,"settingSendCookies":true,"settingDisableRenderRequestBody":false,"settingEncodeUrl":true,"settingRebuildPath":true,"settingFollowRedirects":"global","_type":"request"},{"_id":"env_3bbbbcb07550b0d43ca76b338558b12c53429f03","parentId":"wrk_e521a4a9150542dba55e917aca255462","modified":1640930393849,"created":1640930393849,"name":"Base Environment","data":{},"dataPropertyOrder":null,"color":null,"isPrivate":false,"metaSortKey":1640930393849,"_type":"environment"},{"_id":"jar_3bbbbcb07550b0d43ca76b338558b12c53429f03","parentId":"wrk_e521a4a9150542dba55e917aca255462","modified":1640930393857,"created":1640930393857,"name":"Default Jar","cookies":[],"_type":"cookie_jar"},{"_id":"spc_00ff5f124c0d44149f18ca2dc934742a","parentId":"wrk_e521a4a9150542dba55e917aca255462","modified":1640930393781,"created":1640930393781,"fileName":"avatar","contents":"","contentType":"yaml","_type":"api_spec"}]}